pyvacon/__init__.py
pyvacon/_converter.py
pyvacon/_enum_creator.py
pyvacon/_pyvacon_swig.pyd
pyvacon/pyvacon_swig.py
pyvacon/version.py
pyvacon/finance/__init__.py
pyvacon/finance/calibration/__init__.py
pyvacon/finance/calibration/_classes.py
pyvacon/finance/configuration/__init__.py
pyvacon/finance/configuration/_classes.py
pyvacon/finance/definition/__init__.py
pyvacon/finance/definition/_classes.py
pyvacon/finance/interface/__init__.py
pyvacon/finance/interface/_classes.py
pyvacon/finance/marketdata/__init__.py
pyvacon/finance/marketdata/_classes.py
pyvacon/finance/model/__init__.py
pyvacon/finance/model/_classes.py
pyvacon/finance/pricing/__init__.py
pyvacon/finance/pricing/_classes.py
pyvacon/finance/serialization/__init__.py
pyvacon/finance/serialization/_classes.py
pyvacon/finance/specification/__init__.py
pyvacon/finance/specification/_classes.py
pyvacon/finance/utils/__init__.py
pyvacon/finance/utils/_classes.py
pyvacon/numerics/__init__.py
pyvacon/numerics/extrapolation/__init__.py
pyvacon/numerics/extrapolation/_classes.py
pyvacon/numerics/interpolation/__init__.py
pyvacon/numerics/interpolation/_classes.py
pyvacon/numerics/linearalgebra/__init__.py
pyvacon/numerics/linearalgebra/_classes.py
pyvacon/numerics/optimization/__init__.py
pyvacon/numerics/optimization/_classes.py
pyvacon/numerics/regression/__init__.py
pyvacon/numerics/regression/_classes.py
pyvacon/utilities/__init__.py
pyvacon/utilities/_classes.py
pyvamark/__init__.py
pyvamark/_converter.py
pyvamark/_enum_creator.py
pyvamark/pyvamark_swig.py
pyvamark/setup.py
pyvamark/version.py
pyvamark/database/__init__.py
pyvamark/database/_classes.py
pyvamark/executionutilities/__init__.py
pyvamark/executionutilities/_classes.py
pyvamark/finance/__init__.py
pyvamark/finance/calibration/__init__.py
pyvamark/finance/calibration/_classes.py
pyvamark/finance/configuration/__init__.py
pyvamark/finance/configuration/_classes.py
pyvamark/finance/definition/__init__.py
pyvamark/finance/definition/_classes.py
pyvacon-0.2.0.dist-info/LICENSE
pyvacon-0.2.0.dist-info/METADATA
pyvacon-0.2.0.dist-info/WHEEL
pyvacon-0.2.0.dist-info/top_level.txt
pyvacon-0.2.0.dist-info/RECORD
