Metadata-Version: 2.2
Name: pyvacon
Version: 0.2.0
Summary: frontmark derivatives pricing python package
Home-page: https://github.com/frontmark/
Author: frontmark team
Author-email: info@frontmark.de
License: LICENSE
Classifier: Programming Language :: Python :: 3
Classifier: Programming Language :: C++
Classifier: License :: OSI Approved :: MIT License
Classifier: Operating System :: Microsoft :: Windows
Classifier: Operating System :: POSIX :: Linux
Requires-Python: ==3.11.*
License-File: LICENSE
Dynamic: author
Dynamic: author-email
Dynamic: classifier
Dynamic: description
Dynamic: description-content-type
Dynamic: home-page
Dynamic: keywords
Dynamic: license
Dynamic: requires-python
Dynamic: summary
